[
  {
    "source_title": "荒泷生命摇滚虹色大巡回·下「是荒泷生命摇滚虹色大巡回」",
    "speaker": "托马",
    "text": "真厉害啊，宵宫小姐。居然把烟花送到了这么远的地方。"
  },
  {
    "source_title": "荒泷生命摇滚虹色大巡回·下「是荒泷生命摇滚虹色大巡回」",
    "speaker": "托马",
    "text": "哈哈，这下真要好好感谢荒泷派了，要不是他们办的这个活动，还不知道什么时候能跟旅行者再见。"
  },
  {
    "source_title": "荒泷生命摇滚虹色大巡回·下「是荒泷生命摇滚虹色大巡回」",
    "speaker": "托马",
    "text": "说得没错，虽然旅途很重要，但是累了要记得回来休息，有我们负责接风洗尘。"
  },
  {
    "source_title": "荒泷生命摇滚虹色大巡回·下「是荒泷生命摇滚虹色大巡回」",
    "speaker": "托马",
    "text": "可真是难倒我了，看来我的朋友里面还少了一只关键的狗啊，哈哈。"
  },
  {
    "source_title": "荒泷生命摇滚虹色大巡回·下「是荒泷生命摇滚虹色大巡回」",
    "speaker": "托马",
    "text": "不过如果说真有这么一件事，我觉得跟海祇岛有关。"
  },
  {
    "source_title": "荒泷生命摇滚虹色大巡回·下「是荒泷生命摇滚虹色大巡回」",
    "speaker": "托马",
    "text": "因为不管那家伙身手多好，要想不留痕迹、神出鬼没地出入战场，得有人帮忙掩盖行踪才行吧。"
  },
  {
    "source_title": "荒泷生命摇滚虹色大巡回·下「是荒泷生命摇滚虹色大巡回」",
    "speaker": "托马",
    "text": "据我所知，幕府军中不存在这种事。"
  },
  {
    "source_title": "荒泷生命摇滚虹色大巡回·下「是荒泷生命摇滚虹色大巡回」",
    "speaker": "托马",
    "text": "所以依我看，更大的可能，这是德沃沙克先生编出来的故事，为了表达某种东西。"
  },
  {
    "source_title": "荒泷生命摇滚虹色大巡回·下「是荒泷生命摇滚虹色大巡回」",
    "speaker": "托马",
    "text": "毕竟他是个摇滚艺术家，就是负责用摇滚来表达我们不懂的东西吧？"
  },
  {
    "source_title": "荒泷生命摇滚虹色大巡回·下「是荒泷生命摇滚虹色大巡回」",
    "speaker": "托马",
    "text": "艺术吗？织毛衣算不算？"
  },
  {
    "source_title": "荒泷生命摇滚虹色大巡回·下「是荒泷生命摇滚虹色大巡回」",
    "speaker": "托马",
    "text": "但是感觉不怎么摇滚的样子，今天的场合就完全用不上啊。"
  },
  {
    "source_title": "荒泷生命摇滚虹色大巡回·下「是荒泷生命摇滚虹色大巡回」",
    "speaker": "托马",
    "text": "欸？好主意！下次我试试。"
  },
  {
    "source_title": "荒泷生命摇滚虹色大巡回·下「是荒泷生命摇滚虹色大巡回」",
    "speaker": "托马",
    "text": "跟我以前听过的也不一样…可能是一种新奇的摇滚类型吧。"
  },
  {
    "source_title": "荒泷生命摇滚虹色大巡回·下「是荒泷生命摇滚虹色大巡回」",
    "speaker": "托马",
    "text": "没错，简直让我们大开眼界！"
  },
  {
    "source_title": "荒泷生命摇滚虹色大巡回·下「是荒泷生命摇滚虹色大巡回」",
    "speaker": "托马",
    "text": "难怪…我刚才就觉得，摇滚精神就像歌里的那只鬼兜虫，遇到什么困难都不会害怕，勇往直前地冲刺。"
  },
  {
    "source_title": "荒泷生命摇滚虹色大巡回·下「是荒泷生命摇滚虹色大巡回」",
    "speaker": "托马",
    "text": "看来不是我的感受能力太差，哈哈。"
  },
  {
    "source_title": "荒泷生命摇滚虹色大巡回·下「是荒泷生命摇滚虹色大巡回」",
    "speaker": "托马",
    "text": "哈哈！这样看，忍小姐的摇滚精神是保护荒泷派。"
  }
]